example/__init__.py
example/views.py
muffin_debugtoolbar/__init__.py
muffin_debugtoolbar/panels.py
muffin_debugtoolbar/plugin.py
muffin_debugtoolbar/utils.py
muffin_debugtoolbar/static/css/bootstrap.min.css
muffin_debugtoolbar/static/css/dashboard.css
muffin_debugtoolbar/static/css/debugger.css
muffin_debugtoolbar/static/css/toolbar.css
muffin_debugtoolbar/static/css/toolbar_button.css
muffin_debugtoolbar/static/font/FONT_LICENSE
muffin_debugtoolbar/static/font/ubuntu.ttf
muffin_debugtoolbar/static/fonts/glyphicons-halflings-regular.eot
muffin_debugtoolbar/static/fonts/glyphicons-halflings-regular.svg
muffin_debugtoolbar/static/fonts/glyphicons-halflings-regular.ttf
muffin_debugtoolbar/static/fonts/glyphicons-halflings-regular.woff
muffin_debugtoolbar/static/img/aiohttp.svg
muffin_debugtoolbar/static/img/asc.gif
muffin_debugtoolbar/static/img/back.png
muffin_debugtoolbar/static/img/back_hover.png
muffin_debugtoolbar/static/img/bg.gif
muffin_debugtoolbar/static/img/close.png
muffin_debugtoolbar/static/img/close_hover.png
muffin_debugtoolbar/static/img/console.png
muffin_debugtoolbar/static/img/desc.gif
muffin_debugtoolbar/static/img/headerbg.png
muffin_debugtoolbar/static/img/indicator.png
muffin_debugtoolbar/static/img/less.png
muffin_debugtoolbar/static/img/more.png
muffin_debugtoolbar/static/img/muffin.png
muffin_debugtoolbar/static/img/panel_bg.png
muffin_debugtoolbar/static/img/source.png
muffin_debugtoolbar/static/img/tick-red.png
muffin_debugtoolbar/static/img/tick.png
muffin_debugtoolbar/static/js/README.rst
muffin_debugtoolbar/static/js/bootstrap.min.js
muffin_debugtoolbar/static/js/debugger.js
muffin_debugtoolbar/static/js/jquery-1.10.2.min.js
muffin_debugtoolbar/static/js/jquery-1.10.2.min.map
muffin_debugtoolbar/static/js/jquery.cookie.js
muffin_debugtoolbar/static/js/jquery.tablesorter.min.js
muffin_debugtoolbar/static/js/r.js
muffin_debugtoolbar/static/js/require.js
muffin_debugtoolbar/static/js/tests.html
muffin_debugtoolbar/static/js/toolbar.js
muffin_debugtoolbar-0.3.1.dist-info/AUTHORS.rst
muffin_debugtoolbar-0.3.1.dist-info/LICENSE
muffin_debugtoolbar-0.3.1.dist-info/METADATA
muffin_debugtoolbar-0.3.1.dist-info/WHEEL
muffin_debugtoolbar-0.3.1.dist-info/top_level.txt
muffin_debugtoolbar-0.3.1.dist-info/RECORD
